chatter_py/__init__.py
chatter_py/bot.py
chatter_py/chat_client.py
chatter_py/feature.py
chatter_py/message.py
chatter_py-1.0.1.dist-info/LICENSE.txt
chatter_py-1.0.1.dist-info/METADATA
chatter_py-1.0.1.dist-info/WHEEL
chatter_py-1.0.1.dist-info/top_level.txt
chatter_py-1.0.1.dist-info/RECORD
