Metadata-Version: 2.1
Name: chatter-py
Version: 1.0.1
Summary: A lightweight Python framework for building chatbots.
Home-page: https://github.com/nickjfenton/chatter
Author: nickjfenton
Author-email: nickjfenton@yahoo.co.uk
License: MIT
Keywords: chatbot,framework
Platform: UNKNOWN
Classifier: Development Status :: 4 - Beta
Classifier: Intended Audience :: Developers
Classifier: License :: OSI Approved :: MIT License
Classifier: Programming Language :: Python :: 3
Requires-Python: >=3
License-File: LICENSE.txt
